cuequivariance_ops_jax/VERSION
cuequivariance_ops_jax/__init__.py
cuequivariance_ops_jax/_common.py
cuequivariance_ops_jax/_cublas_enums.py
cuequivariance_ops_jax/_gpu_utilities.py
cuequivariance_ops_jax/_indexed_linear.py
cuequivariance_ops_jax/_tensor_product_uniform_1d_jit.py
cuequivariance_ops_jax/_triangle_attention.py
cuequivariance_ops_jax/_version.py
cuequivariance_ops_jax/lib/libcue_ops_jax.so
cuequivariance_ops_jax_cu12-0.8.1.dist-info/METADATA
cuequivariance_ops_jax_cu12-0.8.1.dist-info/WHEEL
cuequivariance_ops_jax_cu12-0.8.1.dist-info/RECORD
cuequivariance_ops_jax_cu12-0.8.1.dist-info/licenses/LICENSE
cuequivariance_ops_jax_cu12-0.8.1.dist-info/licenses/Third_party_attr.txt
